nimagen/__init__.py
nimagen/genes.py
nimagen/graph.py
nimagen/stats.py
nimagen/visualisation.py
nimagen-0.0.3.dist-info/LICENSE
nimagen-0.0.3.dist-info/METADATA
nimagen-0.0.3.dist-info/WHEEL
nimagen-0.0.3.dist-info/top_level.txt
nimagen-0.0.3.dist-info/RECORD
