Metadata-Version: 2.1
Name: nimagen
Version: 0.0.3
Summary: Simple statistical and visualisation tool for neuroimaging genetics studies
Author-email: Hai Le <l.haimcl@gmail.com>
Project-URL: Homepage, https://github.com/lehai-ml/nimagen
Classifier: Programming Language :: Python :: 3
Classifier: License :: OSI Approved :: MIT License
Classifier: Operating System :: OS Independent
Requires-Python: >=3
License-File: LICENSE
